{
	"format_version": "1.16.100",
	"minecraft:recipe_shaped": {
		"description": {
			"identifier": "medieval:crimson_box1"
		},
		"tags": [
			"workbench"
		],
		"pattern": [
			"ABA",
			"BCB",
			"ABA"
		],
		"key": {
			"A": {
				"item": "medieval:crimson_wood_post"
			},
			"B": {
				"item": "medieval:crimson_wood_beam_right_inclined"
			},
			"C": {
				"item": "minecraft:crimson_planks"
			}
		},
		"unlock": [
			{"item": "athos_misc:nether_book"}
		],
		"result": {
			"item": "medieval:crimson_box1",
			"count": 2
		}
	}
}