{
	"format_version": "1.20.30",
	"minecraft:recipe_shaped": {
		"description": {
			"identifier": "mr:blue_concrete_counter_mr"
		},
		"tags": [
			"workbench"
		],
		"pattern": [
			"###",
			"AAA",
			"AAA"
		],
		"key": {
			"#": {
				"item": "minecraft:blue_concrete"
			},
			"A": {
				"item": "minecraft:white_concrete"
			}
		},
		"unlock": [
			{"item": "minecraft:blue_concrete"},
			{"item": "minecraft:white_concrete"}
		],
		"result": {
			"item": "mr:blue_concrete_counter_mr",
			"count": 9
		}
	}
}